{
  "packages": [
    {
      "id": "essentials",
      "name": "COMPUTER Essentials",
      "version": "1.0.0",
      "description": "The core foundation every COMPUTER installation needs. Includes the event bus, configuration system, UI panel server, and settings management.",
      "author": "COMPUTER Systems",
      "icon": "box",
      "plugins": ["core", "ui", "settings"],
      "tags": ["core", "official", "recommended"]
    },
    {
      "id": "developer-tools",
      "name": "Developer Tools Pack",
      "version": "1.0.0",
      "description": "Everything you need to build, debug, and test COMPUTER plugins. Includes the dev bridge with hot-reload and debugging tools.",
      "author": "Community Labs",
      "icon": "code",
      "plugins": ["core", "dev-bridge"],
      "tags": ["development", "debugging"]
    }
  ]
}
